README.md
setup.py
upimg/__init__.py
upimg/cli.py
upimg/upload.py
upimg/utils.py
upimg.egg-info/PKG-INFO
upimg.egg-info/SOURCES.txt
upimg.egg-info/dependency_links.txt
upimg.egg-info/entry_points.txt
upimg.egg-info/requires.txt
upimg.egg-info/top_level.txt
upimg/sys_platform/__init__.py
upimg/sys_platform/mac.py
upimg/sys_platform/notification.ico
upimg/sys_platform/windows.py