Metadata-Version: 2.1
Name: upimg
Version: 0.1.7
Summary: A CLI tool to genarate Markdown links from clipboard
Home-page: https://github.com/mocobk/upimg
Author: mocobk
Author-email: mailmzb@163.com
License: MIT
Platform: UNKNOWN
Classifier: License :: OSI Approved :: MIT License
Classifier: Programming Language :: Python
Classifier: Programming Language :: Python :: 3
Classifier: Programming Language :: Python :: 3.4
Classifier: Programming Language :: Python :: 3.5
Classifier: Programming Language :: Python :: 3.6
Classifier: Programming Language :: Python :: 3.7
